consentiumthings/__init__.py
consentiumthings/consentiumthings.py
consentiumthings-1.0.1.dist-info/licenses/LICENSE
consentiumthings-1.0.1.dist-info/METADATA
consentiumthings-1.0.1.dist-info/WHEEL
consentiumthings-1.0.1.dist-info/top_level.txt
consentiumthings-1.0.1.dist-info/RECORD
