Metadata-Version: 2.4
Name: consentiumthings
Version: 1.0.1
Summary: Python lib for sending sensor data to Consentium IoT server.
Home-page: https://github.com/ConsentiumIoT/consentiumthings-py
Author: Consentium IoT
Author-email: official@consentiumiot.com
Keywords: Python,IoT,Internet of Things,Sensor Data,Consentium IoT
Classifier: Development Status :: 3 - Alpha
Classifier: Intended Audience :: Developers
Classifier: Topic :: Software Development :: Libraries
Classifier: License :: OSI Approved :: MIT License
Classifier: Programming Language :: Python :: 3
Classifier: Programming Language :: Python :: 3.7
Classifier: Programming Language :: Python :: 3.8
Classifier: Programming Language :: Python :: 3.9
Classifier: Programming Language :: Python :: 3.10
Classifier: Operating System :: OS Independent
Requires-Python: >=3.7
License-File: LICENSE
Requires-Dist: requests
Dynamic: author
Dynamic: author-email
Dynamic: classifier
Dynamic: description
Dynamic: description-content-type
Dynamic: home-page
Dynamic: keywords
Dynamic: license-file
Dynamic: requires-dist
Dynamic: requires-python
Dynamic: summary
